MANIFEST.in
README.rst
multipath.py
requirements.txt
setup.cfg
setup.py
multipath.egg-info/PKG-INFO
multipath.egg-info/SOURCES.txt
multipath.egg-info/dependency_links.txt
multipath.egg-info/top_level.txt