Metadata-Version: 1.1
Name: multipath
Version: 0.0.2
Summary: A miniscule python package for joining and resolving paths against multiple possible directories.A python package for resolving relative paths against multiple root directories
Home-page: https://github.com/adamkewley/multipath
Author: Adam Kewley
Author-email: contact@adamkewley.com
License: Apache License 2.0
Download-URL: https://github.com/adamkewley/multipath/tarball/0.0.2
Platform: UNKNOWN
Classifier: Development Status :: 3 - Alpha
Classifier: Intended Audience :: Developers
Classifier: Programming Language :: Python :: 3
